scrapy_webshare/__init__.py
scrapy_webshare/middleware.py
scrapy_webshare-0.1.0.dist-info/METADATA
scrapy_webshare-0.1.0.dist-info/RECORD
scrapy_webshare-0.1.0.dist-info/WHEEL
scrapy_webshare-0.1.0.dist-info/top_level.txt
